visjobs/__init__.py
visjobs-0.2.dist-info/LICENSE
visjobs-0.2.dist-info/METADATA
visjobs-0.2.dist-info/WHEEL
visjobs-0.2.dist-info/top_level.txt
visjobs-0.2.dist-info/RECORD
