Metadata-Version: 2.1
Name: visjobs
Version: 0.2
Summary: Get Latest Atmospheric Model Data | Analyse | Visualize Easily
Home-page: https://github.com/donmezkutay/visjobs
Author: Kutay Donmez & Berkay Donmez
Author-email: donmezk@outlook.com
License: UNKNOWN
Platform: UNKNOWN
Classifier: Programming Language :: Python :: 3
Classifier: License :: OSI Approved :: MIT License
Classifier: Operating System :: OS Independent
Requires-Python: >=3.6
